easyio/__init__.py
easyio/inp.py
easyio/out.py
easyio/types.py
easyio-0.1.3.dist-info/LICENSE
easyio-0.1.3.dist-info/METADATA
easyio-0.1.3.dist-info/WHEEL
easyio-0.1.3.dist-info/top_level.txt
easyio-0.1.3.dist-info/RECORD
