Metadata-Version: 2.1
Name: easyio
Version: 0.1.3
Summary: Easy-to-use input and output functions
Author-email: Casey Devet <cjdevet@gmail.com>
License: Copyright 2022 Casey Devet        
Project-URL: Homepage, https://github.com/mrdevet/easyio
Keywords: input,output,io
Classifier: License :: OSI Approved :: MIT License
Classifier: Programming Language :: Python :: 3
Requires-Python: >=3
License-File: LICENSE
